aira_cli/__init__.py
aira_cli/config.py
aira_cli/docker.py
aira_cli/main.py
aira_cli/network.py
aira_cli/setup.py
aira_cli/storage.py
aira_cli/system.py
aira_cli/utils.py
aira_cli-0.1.0.dist-info/METADATA
aira_cli-0.1.0.dist-info/WHEEL
aira_cli-0.1.0.dist-info/entry_points.txt
aira_cli-0.1.0.dist-info/top_level.txt
aira_cli-0.1.0.dist-info/RECORD
