Metadata-Version: 2.1
Name: aira-cli
Version: 0.1.0
Summary: AIRA CLI for managing a home server and the AIRA AI Platform
Home-page: https://github.com/yourusername/aira_cli
Author: Your Name
Author-email: your.email@example.com
Classifier: Programming Language :: Python :: 3
Classifier: License :: OSI Approved :: MIT License
Classifier: Operating System :: OS Independent
Requires-Python: >=3.6
